{
  "task_summary": "Design and implement a simple event bus system in Python that enables decoupled communication between components using the Observer pattern. The system allows publishers to broadcast events to multiple subscribers without tight coupling.",
  "chosen_approach": "Observer Pattern with a central EventBus class that maintains a registry of event names to callback functions. This approach is simple, synchronous, and uses only Python standard library features without external dependencies.",
  "components": [
    {
      "name": "Event",
      "responsibility": "Represents a single event occurrence with a name and optional payload data",
      "functions": [
        {
          "name": "__init__",
          "description": "Initialize Event with name and payload",
          "parameters": [
            {
              "name": "name",
              "type_hint": "str",
              "description": "Unique identifier for the event",
              "required": true,
              "default": null
            },
            {
              "name": "payload",
              "type_hint": "Any",
              "description": "Optional data associated with the event",
              "required": false,
              "default": "null"
            }
          ],
          "returns": "None",
          "raises": [],
          "notes": "Basic constructor for event data container"
        },
        {
          "name": "to_dict",
          "description": "Serialize event to dictionary for debugging or logging",
          "parameters": [],
          "returns": "dict",
          "raises": [],
          "notes": "Optional utility method for introspection"
        }
      ],
      "dependencies": [],
      "data_structures": [
        "name: str",
        "payload: Any"
      ],
      "interface_inputs": [],
      "interface_outputs": [
        "name: str",
        "payload: Any"
      ]
    },
    {
      "name": "EventBus",
      "responsibility": "Central registry that manages event subscriptions and publishes events to registered callbacks",
      "functions": [
        {
          "name": "__init__",
          "description": "Initialize EventBus with empty subscriber registry",
          "parameters": [],
          "returns": "None",
          "raises": [],
          "notes": "Creates internal _subscribers dictionary"
        },
        {
          "name": "subscribe",
          "description": "Register a callback function to be called when an event is published",
          "parameters": [
            {
              "name": "event_name",
              "type_hint": "str",
              "description": "Name of the event to subscribe to",
              "required": true,
              "default": null
            },
            {
              "name": "callback",
              "type_hint": "Callable[[Event], None]",
              "description": "Function to invoke when event is published",
              "required": true,
              "default": null
            }
          ],
          "returns": "None",
          "raises": [
            "ValueError"
          ],
          "notes": "Raises if event_name is empty"
        },
        {
          "name": "unsubscribe",
          "description": "Remove a specific callback from event subscriptions",
          "parameters": [
            {
              "name": "event_name",
              "type_hint": "str",
              "description": "Name of the event to unsubscribe from",
              "required": true,
              "default": null
            },
            {
              "name": "callback",
              "type_hint": "Callable[[Event], None]",
              "description": "Callback function to remove",
              "required": true,
              "default": null
            }
          ],
          "returns": "None",
          "raises": [
            "ValueError"
          ],
          "notes": "Raises if event or callback not found"
        },
        {
          "name": "publish",
          "description": "Create and dispatch an event to all registered subscribers",
          "parameters": [
            {
              "name": "event_name",
              "type_hint": "str",
              "description": "Name of the event to publish",
              "required": true,
              "default": null
            },
            {
              "name": "payload",
              "type_hint": "Any",
              "description": "Data to attach to the event",
              "required": false,
              "default": "null"
            }
          ],
          "returns": "None",
          "raises": [],
          "notes": "Continues calling remaining callbacks even if one fails"
        },
        {
          "name": "clear_subscribers",
          "description": "Remove all subscribers for a specific event",
          "parameters": [
            {
              "name": "event_name",
              "type_hint": "str",
              "description": "Name of the event to clear",
              "required": true,
              "default": null
            }
          ],
          "returns": "None",
          "raises": [],
          "notes": "Helper method for cleanup"
        }
      ],
      "dependencies": [
        "Event"
      ],
      "data_structures": [
        "_subscribers: Dict[str, List[Callable]]"
      ],
      "interface_inputs": [
        "subscribe(event_name, callback)",
        "unsubscribe(event_name, callback)",
        "publish(event_name, payload)"
      ],
      "interface_outputs": [
        "Event instances dispatched to callbacks"
      ]
    }
  ],
  "implementation_order": [
    "Event",
    "EventBus"
  ],
  "shared_data_structures": [
    "Event class with name and payload attributes",
    "Dictionary mapping event names to callback lists"
  ],
  "edge_cases": [
    "Empty event name should raise ValueError",
    "Unsubscribing non-existent callback should raise ValueError",
    "Callback execution failure should not halt remaining callbacks",
    "Publishing to event with no subscribers should be no-op",
    "Duplicate subscription of same callback should call it multiple times"
  ],
  "assumptions": [
    "Single-threaded execution model for simplicity",
    "Synchronous callbacks (no async/await)",
    "Python 3.8+ with type hints",
    "No need for thread safety or persistence",
    "Callback functions must accept Event object as parameter"
  ],
  "external_dependencies": [],
  "moe_routing_context": "Python synchronous event-driven architecture using Observer pattern, typing module for type hints, standard library only, no external packages required",
  "dropped_ideas": [],
  "confidence_in_plan": "high"
}